[
  "{\"datetime\":\"Fri Mar 18 2022 12:31:36 GMT-0700 (Pacific Daylight Time)\",\"node\":\"https://chrysalis-nodes.iota.org/\",\"timeToSync\":1393,\"timeToReceiveMessage\":5168}",
  "{\"datetime\":\"Fri Mar 18 2022 12:31:38 GMT-0700 (Pacific Daylight Time)\",\"node\":\"https://chrysalis-nodes.iota.org/\",\"timeToSync\":501,\"timeToReceiveMessage\":1635}",
  "{\"datetime\":\"Fri Mar 18 2022 12:32:53 GMT-0700 (Pacific Daylight Time)\",\"node\":\"https://chrysalis-nodes.iota.org/\",\"timeToSync\":1210,\"timeToReceiveMessage\":1785}",
  "{\"datetime\":\"Fri Mar 18 2022 12:32:57 GMT-0700 (Pacific Daylight Time)\",\"node\":\"https://chrysalis-nodes.iota.org/\",\"timeToSync\":509,\"timeToReceiveMessage\":3277}",
  "{\"datetime\":\"Fri Mar 18 2022 12:33:03 GMT-0700 (Pacific Daylight Time)\",\"node\":\"https://chrysalis-nodes.iota.org/\",\"timeToSync\":556,\"timeToReceiveMessage\":5612}",
  "{\"datetime\":\"Fri Mar 18 2022 12:33:08 GMT-0700 (Pacific Daylight Time)\",\"node\":\"https://chrysalis-nodes.iota.org/\",\"timeToSync\":696,\"timeToReceiveMessage\":3723}",
  "{\"datetime\":\"Fri Mar 18 2022 12:33:10 GMT-0700 (Pacific Daylight Time)\",\"node\":\"https://chrysalis-nodes.iota.org/\",\"timeToSync\":577,\"timeToReceiveMessage\":1741}",
  "{\"datetime\":\"Fri Mar 18 2022 12:33:12 GMT-0700 (Pacific Daylight Time)\",\"node\":\"https://chrysalis-nodes.iota.org/\",\"timeToSync\":446,\"timeToReceiveMessage\":1499}",
  "{\"datetime\":\"Fri Mar 18 2022 12:33:14 GMT-0700 (Pacific Daylight Time)\",\"node\":\"https://chrysalis-nodes.iota.org/\",\"timeToSync\":510,\"timeToReceiveMessage\":1653}",
  "{\"datetime\":\"Fri Mar 18 2022 12:33:17 GMT-0700 (Pacific Daylight Time)\",\"node\":\"https://chrysalis-nodes.iota.org/\",\"timeToSync\":489,\"timeToReceiveMessage\":2110}",
  "{\"datetime\":\"Fri Mar 18 2022 12:33:23 GMT-0700 (Pacific Daylight Time)\",\"node\":\"https://chrysalis-nodes.iota.org/\",\"timeToSync\":503,\"timeToReceiveMessage\":6216}",
  "{\"datetime\":\"Fri Mar 18 2022 12:33:29 GMT-0700 (Pacific Daylight Time)\",\"node\":\"https://chrysalis-nodes.iota.org/\",\"timeToSync\":596,\"timeToReceiveMessage\":4713}",
  "{\"datetime\":\"Fri Mar 18 2022 12:33:31 GMT-0700 (Pacific Daylight Time)\",\"node\":\"https://chrysalis-nodes.iota.org/\",\"timeToSync\":461,\"timeToReceiveMessage\":1748}",
  "{\"datetime\":\"Fri Mar 18 2022 12:33:35 GMT-0700 (Pacific Daylight Time)\",\"node\":\"https://chrysalis-nodes.iota.org/\",\"timeToSync\":462,\"timeToReceiveMessage\":3597}",
  "{\"datetime\":\"Fri Mar 18 2022 12:33:42 GMT-0700 (Pacific Daylight Time)\",\"node\":\"https://chrysalis-nodes.iota.org/\",\"timeToSync\":546,\"timeToReceiveMessage\":6002}",
  "{\"datetime\":\"Fri Mar 18 2022 12:33:44 GMT-0700 (Pacific Daylight Time)\",\"node\":\"https://chrysalis-nodes.iota.org/\",\"timeToSync\":547,\"timeToReceiveMessage\":1754}",
  "{\"datetime\":\"Fri Mar 18 2022 12:33:48 GMT-0700 (Pacific Daylight Time)\",\"node\":\"https://chrysalis-nodes.iota.org/\",\"timeToSync\":488,\"timeToReceiveMessage\":3300}",
  "{\"datetime\":\"Fri Mar 18 2022 12:33:56 GMT-0700 (Pacific Daylight Time)\",\"node\":\"https://chrysalis-nodes.iota.org/\",\"timeToSync\":502,\"timeToReceiveMessage\":8299}",
  "{\"datetime\":\"Fri Mar 18 2022 12:33:59 GMT-0700 (Pacific Daylight Time)\",\"node\":\"https://chrysalis-nodes.iota.org/\",\"timeToSync\":514,\"timeToReceiveMessage\":1954}",
  "{\"datetime\":\"Fri Mar 18 2022 12:34:02 GMT-0700 (Pacific Daylight Time)\",\"node\":\"https://chrysalis-nodes.iota.org/\",\"timeToSync\":501,\"timeToReceiveMessage\":2598}",
  "{\"datetime\":\"Fri Mar 18 2022 12:34:06 GMT-0700 (Pacific Daylight Time)\",\"node\":\"https://chrysalis-nodes.iota.org/\",\"timeToSync\":482,\"timeToReceiveMessage\":3677}",
  "{\"datetime\":\"Fri Mar 18 2022 12:34:09 GMT-0700 (Pacific Daylight Time)\",\"node\":\"https://chrysalis-nodes.iota.org/\",\"timeToSync\":482,\"timeToReceiveMessage\":2017}",
  "{\"datetime\":\"Fri Mar 18 2022 12:34:13 GMT-0700 (Pacific Daylight Time)\",\"node\":\"https://chrysalis-nodes.iota.org/\",\"timeToSync\":481,\"timeToReceiveMessage\":3769}",
  "{\"datetime\":\"Fri Mar 18 2022 12:34:16 GMT-0700 (Pacific Daylight Time)\",\"node\":\"https://chrysalis-nodes.iota.org/\",\"timeToSync\":658,\"timeToReceiveMessage\":2411}",
  "{\"datetime\":\"Fri Mar 18 2022 12:34:19 GMT-0700 (Pacific Daylight Time)\",\"node\":\"https://chrysalis-nodes.iota.org/\",\"timeToSync\":560,\"timeToReceiveMessage\":2110}",
  "{\"datetime\":\"Fri Mar 18 2022 12:34:22 GMT-0700 (Pacific Daylight Time)\",\"node\":\"https://chrysalis-nodes.iota.org/\",\"timeToSync\":487,\"timeToReceiveMessage\":2821}",
  "{\"datetime\":\"Fri Mar 18 2022 12:34:26 GMT-0700 (Pacific Daylight Time)\",\"node\":\"https://chrysalis-nodes.iota.org/\",\"timeToSync\":471,\"timeToReceiveMessage\":3278}",
  "{\"datetime\":\"Fri Mar 18 2022 12:34:29 GMT-0700 (Pacific Daylight Time)\",\"node\":\"https://chrysalis-nodes.iota.org/\",\"timeToSync\":512,\"timeToReceiveMessage\":2549}",
  "{\"datetime\":\"Fri Mar 18 2022 12:34:38 GMT-0700 (Pacific Daylight Time)\",\"node\":\"https://chrysalis-nodes.iota.org/\",\"timeToSync\":485,\"timeToReceiveMessage\":8593}",
  "{\"datetime\":\"Fri Mar 18 2022 12:34:40 GMT-0700 (Pacific Daylight Time)\",\"node\":\"https://chrysalis-nodes.iota.org/\",\"timeToSync\":619,\"timeToReceiveMessage\":1550}",
  "{\"datetime\":\"Fri Mar 18 2022 12:34:44 GMT-0700 (Pacific Daylight Time)\",\"node\":\"https://chrysalis-nodes.iota.org/\",\"timeToSync\":530,\"timeToReceiveMessage\":3289}",
  "{\"datetime\":\"Fri Mar 18 2022 12:34:47 GMT-0700 (Pacific Daylight Time)\",\"node\":\"https://chrysalis-nodes.iota.org/\",\"timeToSync\":584,\"timeToReceiveMessage\":2822}",
  "{\"datetime\":\"Fri Mar 18 2022 12:34:54 GMT-0700 (Pacific Daylight Time)\",\"node\":\"https://chrysalis-nodes.iota.org/\",\"timeToSync\":518,\"timeToReceiveMessage\":5932}",
  "{\"datetime\":\"Fri Mar 18 2022 12:34:57 GMT-0700 (Pacific Daylight Time)\",\"node\":\"https://chrysalis-nodes.iota.org/\",\"timeToSync\":479,\"timeToReceiveMessage\":3012}",
  "{\"datetime\":\"Fri Mar 18 2022 12:35:00 GMT-0700 (Pacific Daylight Time)\",\"node\":\"https://chrysalis-nodes.iota.org/\",\"timeToSync\":543,\"timeToReceiveMessage\":2112}",
  "{\"datetime\":\"Fri Mar 18 2022 12:35:05 GMT-0700 (Pacific Daylight Time)\",\"node\":\"https://chrysalis-nodes.iota.org/\",\"timeToSync\":519,\"timeToReceiveMessage\":4490}",
  "{\"datetime\":\"Fri Mar 18 2022 12:35:21 GMT-0700 (Pacific Daylight Time)\",\"node\":\"https://chrysalis-nodes.iota.org/\",\"timeToSync\":499,\"timeToReceiveMessage\":15660}",
  "{\"datetime\":\"Fri Mar 18 2022 12:35:24 GMT-0700 (Pacific Daylight Time)\",\"node\":\"https://chrysalis-nodes.iota.org/\",\"timeToSync\":480,\"timeToReceiveMessage\":2980}",
  "{\"datetime\":\"Fri Mar 18 2022 12:35:30 GMT-0700 (Pacific Daylight Time)\",\"node\":\"https://chrysalis-nodes.iota.org/\",\"timeToSync\":487,\"timeToReceiveMessage\":5333}",
  "{\"datetime\":\"Fri Mar 18 2022 12:35:33 GMT-0700 (Pacific Daylight Time)\",\"node\":\"https://chrysalis-nodes.iota.org/\",\"timeToSync\":598,\"timeToReceiveMessage\":2201}",
  "{\"datetime\":\"Fri Mar 18 2022 12:35:39 GMT-0700 (Pacific Daylight Time)\",\"node\":\"https://chrysalis-nodes.iota.org/\",\"timeToSync\":484,\"timeToReceiveMessage\":5766}",
  "{\"datetime\":\"Fri Mar 18 2022 12:35:45 GMT-0700 (Pacific Daylight Time)\",\"node\":\"https://chrysalis-nodes.iota.org/\",\"timeToSync\":461,\"timeToReceiveMessage\":5148}",
  "{\"datetime\":\"Fri Mar 18 2022 12:35:47 GMT-0700 (Pacific Daylight Time)\",\"node\":\"https://chrysalis-nodes.iota.org/\",\"timeToSync\":465,\"timeToReceiveMessage\":1765}",
  "{\"datetime\":\"Fri Mar 18 2022 12:35:50 GMT-0700 (Pacific Daylight Time)\",\"node\":\"https://chrysalis-nodes.iota.org/\",\"timeToSync\":468,\"timeToReceiveMessage\":2017}",
  "{\"datetime\":\"Fri Mar 18 2022 12:35:52 GMT-0700 (Pacific Daylight Time)\",\"node\":\"https://chrysalis-nodes.iota.org/\",\"timeToSync\":518,\"timeToReceiveMessage\":2089}",
  "{\"datetime\":\"Fri Mar 18 2022 12:35:58 GMT-0700 (Pacific Daylight Time)\",\"node\":\"https://chrysalis-nodes.iota.org/\",\"timeToSync\":457,\"timeToReceiveMessage\":5658}",
  "{\"datetime\":\"Fri Mar 18 2022 12:36:01 GMT-0700 (Pacific Daylight Time)\",\"node\":\"https://chrysalis-nodes.iota.org/\",\"timeToSync\":539,\"timeToReceiveMessage\":2240}",
  "{\"datetime\":\"Fri Mar 18 2022 12:36:04 GMT-0700 (Pacific Daylight Time)\",\"node\":\"https://chrysalis-nodes.iota.org/\",\"timeToSync\":464,\"timeToReceiveMessage\":2175}",
  "{\"datetime\":\"Fri Mar 18 2022 12:36:06 GMT-0700 (Pacific Daylight Time)\",\"node\":\"https://chrysalis-nodes.iota.org/\",\"timeToSync\":545,\"timeToReceiveMessage\":2133}",
  "{\"datetime\":\"Fri Mar 18 2022 12:36:09 GMT-0700 (Pacific Daylight Time)\",\"node\":\"https://chrysalis-nodes.iota.org/\",\"timeToSync\":499,\"timeToReceiveMessage\":2243}",
  "{\"datetime\":\"Fri Mar 18 2022 12:36:17 GMT-0700 (Pacific Daylight Time)\",\"node\":\"https://chrysalis-nodes.iota.org/\",\"timeToSync\":480,\"timeToReceiveMessage\":7136}",
  "{\"datetime\":\"Fri Mar 18 2022 12:36:20 GMT-0700 (Pacific Daylight Time)\",\"node\":\"https://chrysalis-nodes.iota.org/\",\"timeToSync\":486,\"timeToReceiveMessage\":2314}",
  "{\"datetime\":\"Fri Mar 18 2022 12:36:26 GMT-0700 (Pacific Daylight Time)\",\"node\":\"https://chrysalis-nodes.iota.org/\",\"timeToSync\":461,\"timeToReceiveMessage\":5809}",
  "{\"datetime\":\"Fri Mar 18 2022 12:36:28 GMT-0700 (Pacific Daylight Time)\",\"node\":\"https://chrysalis-nodes.iota.org/\",\"timeToSync\":538,\"timeToReceiveMessage\":1949}",
  "{\"datetime\":\"Fri Mar 18 2022 12:36:34 GMT-0700 (Pacific Daylight Time)\",\"node\":\"https://chrysalis-nodes.iota.org/\",\"timeToSync\":452,\"timeToReceiveMessage\":4758}",
  "{\"datetime\":\"Fri Mar 18 2022 12:36:37 GMT-0700 (Pacific Daylight Time)\",\"node\":\"https://chrysalis-nodes.iota.org/\",\"timeToSync\":474,\"timeToReceiveMessage\":3014}",
  "{\"datetime\":\"Fri Mar 18 2022 12:36:44 GMT-0700 (Pacific Daylight Time)\",\"node\":\"https://chrysalis-nodes.iota.org/\",\"timeToSync\":440,\"timeToReceiveMessage\":6438}",
  "{\"datetime\":\"Fri Mar 18 2022 12:36:49 GMT-0700 (Pacific Daylight Time)\",\"node\":\"https://chrysalis-nodes.iota.org/\",\"timeToSync\":462,\"timeToReceiveMessage\":4795}",
  "{\"datetime\":\"Fri Mar 18 2022 12:36:55 GMT-0700 (Pacific Daylight Time)\",\"node\":\"https://chrysalis-nodes.iota.org/\",\"timeToSync\":457,\"timeToReceiveMessage\":5403}",
  "{\"datetime\":\"Fri Mar 18 2022 12:36:58 GMT-0700 (Pacific Daylight Time)\",\"node\":\"https://chrysalis-nodes.iota.org/\",\"timeToSync\":486,\"timeToReceiveMessage\":2594}",
  "{\"datetime\":\"Fri Mar 18 2022 12:37:03 GMT-0700 (Pacific Daylight Time)\",\"node\":\"https://chrysalis-nodes.iota.org/\",\"timeToSync\":480,\"timeToReceiveMessage\":4077}",
  "{\"datetime\":\"Fri Mar 18 2022 12:37:07 GMT-0700 (Pacific Daylight Time)\",\"node\":\"https://chrysalis-nodes.iota.org/\",\"timeToSync\":556,\"timeToReceiveMessage\":3304}",
  "{\"datetime\":\"Fri Mar 18 2022 12:37:10 GMT-0700 (Pacific Daylight Time)\",\"node\":\"https://chrysalis-nodes.iota.org/\",\"timeToSync\":548,\"timeToReceiveMessage\":2479}",
  "{\"datetime\":\"Fri Mar 18 2022 12:37:13 GMT-0700 (Pacific Daylight Time)\",\"node\":\"https://chrysalis-nodes.iota.org/\",\"timeToSync\":645,\"timeToReceiveMessage\":2964}",
  "{\"datetime\":\"Fri Mar 18 2022 12:37:17 GMT-0700 (Pacific Daylight Time)\",\"node\":\"https://chrysalis-nodes.iota.org/\",\"timeToSync\":556,\"timeToReceiveMessage\":3557}",
  "{\"datetime\":\"Fri Mar 18 2022 12:37:21 GMT-0700 (Pacific Daylight Time)\",\"node\":\"https://chrysalis-nodes.iota.org/\",\"timeToSync\":587,\"timeToReceiveMessage\":2789}",
  "{\"datetime\":\"Fri Mar 18 2022 12:37:26 GMT-0700 (Pacific Daylight Time)\",\"node\":\"https://chrysalis-nodes.iota.org/\",\"timeToSync\":522,\"timeToReceiveMessage\":4326}",
  "{\"datetime\":\"Fri Mar 18 2022 12:37:28 GMT-0700 (Pacific Daylight Time)\",\"node\":\"https://chrysalis-nodes.iota.org/\",\"timeToSync\":481,\"timeToReceiveMessage\":1757}",
  "{\"datetime\":\"Fri Mar 18 2022 12:37:34 GMT-0700 (Pacific Daylight Time)\",\"node\":\"https://chrysalis-nodes.iota.org/\",\"timeToSync\":526,\"timeToReceiveMessage\":5513}",
  "{\"datetime\":\"Fri Mar 18 2022 12:37:36 GMT-0700 (Pacific Daylight Time)\",\"node\":\"https://chrysalis-nodes.iota.org/\",\"timeToSync\":455,\"timeToReceiveMessage\":1964}",
  "{\"datetime\":\"Fri Mar 18 2022 12:37:39 GMT-0700 (Pacific Daylight Time)\",\"node\":\"https://chrysalis-nodes.iota.org/\",\"timeToSync\":507,\"timeToReceiveMessage\":2462}",
  "{\"datetime\":\"Fri Mar 18 2022 12:37:41 GMT-0700 (Pacific Daylight Time)\",\"node\":\"https://chrysalis-nodes.iota.org/\",\"timeToSync\":481,\"timeToReceiveMessage\":1748}",
  "{\"datetime\":\"Fri Mar 18 2022 12:37:47 GMT-0700 (Pacific Daylight Time)\",\"node\":\"https://chrysalis-nodes.iota.org/\",\"timeToSync\":483,\"timeToReceiveMessage\":4826}",
  "{\"datetime\":\"Fri Mar 18 2022 12:37:49 GMT-0700 (Pacific Daylight Time)\",\"node\":\"https://chrysalis-nodes.iota.org/\",\"timeToSync\":482,\"timeToReceiveMessage\":1828}",
  "{\"datetime\":\"Fri Mar 18 2022 12:37:52 GMT-0700 (Pacific Daylight Time)\",\"node\":\"https://chrysalis-nodes.iota.org/\",\"timeToSync\":494,\"timeToReceiveMessage\":2475}",
  "{\"datetime\":\"Fri Mar 18 2022 12:37:54 GMT-0700 (Pacific Daylight Time)\",\"node\":\"https://chrysalis-nodes.iota.org/\",\"timeToSync\":478,\"timeToReceiveMessage\":1909}",
  "{\"datetime\":\"Fri Mar 18 2022 12:37:58 GMT-0700 (Pacific Daylight Time)\",\"node\":\"https://chrysalis-nodes.iota.org/\",\"timeToSync\":481,\"timeToReceiveMessage\":3436}",
  "{\"datetime\":\"Fri Mar 18 2022 12:38:02 GMT-0700 (Pacific Daylight Time)\",\"node\":\"https://chrysalis-nodes.iota.org/\",\"timeToSync\":479,\"timeToReceiveMessage\":2934}",
  "{\"datetime\":\"Fri Mar 18 2022 12:38:05 GMT-0700 (Pacific Daylight Time)\",\"node\":\"https://chrysalis-nodes.iota.org/\",\"timeToSync\":463,\"timeToReceiveMessage\":2425}",
  "{\"datetime\":\"Fri Mar 18 2022 12:38:18 GMT-0700 (Pacific Daylight Time)\",\"node\":\"https://chrysalis-nodes.iota.org/\",\"timeToSync\":458,\"timeToReceiveMessage\":12831}",
  "{\"datetime\":\"Fri Mar 18 2022 12:38:23 GMT-0700 (Pacific Daylight Time)\",\"node\":\"https://chrysalis-nodes.iota.org/\",\"timeToSync\":481,\"timeToReceiveMessage\":4448}",
  "{\"datetime\":\"Fri Mar 18 2022 12:38:25 GMT-0700 (Pacific Daylight Time)\",\"node\":\"https://chrysalis-nodes.iota.org/\",\"timeToSync\":444,\"timeToReceiveMessage\":1596}",
  "{\"datetime\":\"Fri Mar 18 2022 12:38:27 GMT-0700 (Pacific Daylight Time)\",\"node\":\"https://chrysalis-nodes.iota.org/\",\"timeToSync\":491,\"timeToReceiveMessage\":1730}",
  "{\"datetime\":\"Fri Mar 18 2022 12:38:33 GMT-0700 (Pacific Daylight Time)\",\"node\":\"https://chrysalis-nodes.iota.org/\",\"timeToSync\":513,\"timeToReceiveMessage\":5173}",
  "{\"datetime\":\"Fri Mar 18 2022 12:38:42 GMT-0700 (Pacific Daylight Time)\",\"node\":\"https://chrysalis-nodes.iota.org/\",\"timeToSync\":515,\"timeToReceiveMessage\":8865}",
  "{\"datetime\":\"Fri Mar 18 2022 12:38:47 GMT-0700 (Pacific Daylight Time)\",\"node\":\"https://chrysalis-nodes.iota.org/\",\"timeToSync\":637,\"timeToReceiveMessage\":4051}",
  "{\"datetime\":\"Fri Mar 18 2022 12:38:53 GMT-0700 (Pacific Daylight Time)\",\"node\":\"https://chrysalis-nodes.iota.org/\",\"timeToSync\":485,\"timeToReceiveMessage\":5323}",
  "{\"datetime\":\"Fri Mar 18 2022 12:38:55 GMT-0700 (Pacific Daylight Time)\",\"node\":\"https://chrysalis-nodes.iota.org/\",\"timeToSync\":526,\"timeToReceiveMessage\":2134}",
  "{\"datetime\":\"Fri Mar 18 2022 12:38:57 GMT-0700 (Pacific Daylight Time)\",\"node\":\"https://chrysalis-nodes.iota.org/\",\"timeToSync\":511,\"timeToReceiveMessage\":1580}",
  "{\"datetime\":\"Fri Mar 18 2022 12:39:05 GMT-0700 (Pacific Daylight Time)\",\"node\":\"https://chrysalis-nodes.iota.org/\",\"timeToSync\":455,\"timeToReceiveMessage\":6592}",
  "{\"datetime\":\"Fri Mar 18 2022 12:39:12 GMT-0700 (Pacific Daylight Time)\",\"node\":\"https://chrysalis-nodes.iota.org/\",\"timeToSync\":448,\"timeToReceiveMessage\":7023}",
  "{\"datetime\":\"Fri Mar 18 2022 12:39:18 GMT-0700 (Pacific Daylight Time)\",\"node\":\"https://chrysalis-nodes.iota.org/\",\"timeToSync\":557,\"timeToReceiveMessage\":5031}",
  "{\"datetime\":\"Fri Mar 18 2022 12:39:20 GMT-0700 (Pacific Daylight Time)\",\"node\":\"https://chrysalis-nodes.iota.org/\",\"timeToSync\":472,\"timeToReceiveMessage\":1556}",
  "{\"datetime\":\"Fri Mar 18 2022 12:39:22 GMT-0700 (Pacific Daylight Time)\",\"node\":\"https://chrysalis-nodes.iota.org/\",\"timeToSync\":480,\"timeToReceiveMessage\":1709}",
  "{\"datetime\":\"Fri Mar 18 2022 12:39:26 GMT-0700 (Pacific Daylight Time)\",\"node\":\"https://chrysalis-nodes.iota.org/\",\"timeToSync\":522,\"timeToReceiveMessage\":3228}",
  "{\"datetime\":\"Fri Mar 18 2022 12:39:30 GMT-0700 (Pacific Daylight Time)\",\"node\":\"https://chrysalis-nodes.iota.org/\",\"timeToSync\":497,\"timeToReceiveMessage\":3510}",
  "{\"datetime\":\"Fri Mar 18 2022 12:39:35 GMT-0700 (Pacific Daylight Time)\",\"node\":\"https://chrysalis-nodes.iota.org/\",\"timeToSync\":506,\"timeToReceiveMessage\":4793}",
  "{\"datetime\":\"Fri Mar 18 2022 12:39:39 GMT-0700 (Pacific Daylight Time)\",\"node\":\"https://chrysalis-nodes.iota.org/\",\"timeToSync\":473,\"timeToReceiveMessage\":3807}",
  "{\"datetime\":\"Fri Mar 18 2022 12:39:43 GMT-0700 (Pacific Daylight Time)\",\"node\":\"https://chrysalis-nodes.iota.org/\",\"timeToSync\":540,\"timeToReceiveMessage\":2830}",
  "{\"datetime\":\"Fri Mar 18 2022 12:39:45 GMT-0700 (Pacific Daylight Time)\",\"node\":\"https://chrysalis-nodes.iota.org/\",\"timeToSync\":474,\"timeToReceiveMessage\":2266}",
  "{\"datetime\":\"Fri Mar 18 2022 12:39:51 GMT-0700 (Pacific Daylight Time)\",\"node\":\"https://chrysalis-nodes.iota.org/\",\"timeToSync\":497,\"timeToReceiveMessage\":4883}",
  "{\"datetime\":\"Fri Mar 18 2022 12:39:55 GMT-0700 (Pacific Daylight Time)\",\"node\":\"https://chrysalis-nodes.iota.org/\",\"timeToSync\":503,\"timeToReceiveMessage\":4016}",
  "{\"datetime\":\"Sat Mar 19 2022 12:21:06 GMT-0700 (Pacific Daylight Time)\",\"node\":\"http://54.177.214.21:14265/\",\"timeToSync\":285,\"timeToReceiveMessage\":962}",
  "{\"datetime\":\"Sat Mar 19 2022 12:21:08 GMT-0700 (Pacific Daylight Time)\",\"node\":\"http://54.177.214.21:14265/\",\"timeToSync\":113,\"timeToReceiveMessage\":2343}",
  "{\"datetime\":\"Sat Mar 19 2022 12:21:10 GMT-0700 (Pacific Daylight Time)\",\"node\":\"http://54.177.214.21:14265/\",\"timeToSync\":112,\"timeToReceiveMessage\":1279}",
  "{\"datetime\":\"Sat Mar 19 2022 12:21:11 GMT-0700 (Pacific Daylight Time)\",\"node\":\"http://54.177.214.21:14265/\",\"timeToSync\":109,\"timeToReceiveMessage\":738}",
  "{\"datetime\":\"Sat Mar 19 2022 12:21:13 GMT-0700 (Pacific Daylight Time)\",\"node\":\"http://54.177.214.21:14265/\",\"timeToSync\":106,\"timeToReceiveMessage\":2043}",
  "{\"datetime\":\"Sat Mar 19 2022 12:21:22 GMT-0700 (Pacific Daylight Time)\",\"node\":\"http://54.177.214.21:14265/\",\"timeToSync\":111,\"timeToReceiveMessage\":8609}",
  "{\"datetime\":\"Sat Mar 19 2022 12:21:27 GMT-0700 (Pacific Daylight Time)\",\"node\":\"http://54.177.214.21:14265/\",\"timeToSync\":112,\"timeToReceiveMessage\":5208}",
  "{\"datetime\":\"Sat Mar 19 2022 12:21:29 GMT-0700 (Pacific Daylight Time)\",\"node\":\"http://54.177.214.21:14265/\",\"timeToSync\":109,\"timeToReceiveMessage\":1823}",
  "{\"datetime\":\"Sat Mar 19 2022 12:21:31 GMT-0700 (Pacific Daylight Time)\",\"node\":\"http://54.177.214.21:14265/\",\"timeToSync\":107,\"timeToReceiveMessage\":1560}",
  "{\"datetime\":\"Sat Mar 19 2022 12:21:34 GMT-0700 (Pacific Daylight Time)\",\"node\":\"http://54.177.214.21:14265/\",\"timeToSync\":105,\"timeToReceiveMessage\":3138}",
  "{\"datetime\":\"Sat Mar 19 2022 12:22:50 GMT-0700 (Pacific Daylight Time)\",\"node\":\"http://54.177.214.21:14265/\",\"timeToSync\":283,\"timeToReceiveMessage\":2845}",
  "{\"datetime\":\"Sat Mar 19 2022 12:22:54 GMT-0700 (Pacific Daylight Time)\",\"node\":\"http://54.177.214.21:14265/\",\"timeToSync\":116,\"timeToReceiveMessage\":3907}",
  "{\"datetime\":\"Sat Mar 19 2022 12:23:01 GMT-0700 (Pacific Daylight Time)\",\"node\":\"http://54.177.214.21:14265/\",\"timeToSync\":110,\"timeToReceiveMessage\":6917}",
  "{\"datetime\":\"Sat Mar 19 2022 12:23:01 GMT-0700 (Pacific Daylight Time)\",\"node\":\"http://54.177.214.21:14265/\",\"timeToSync\":110,\"timeToReceiveMessage\":526}",
  "{\"datetime\":\"Sat Mar 19 2022 12:23:06 GMT-0700 (Pacific Daylight Time)\",\"node\":\"http://54.177.214.21:14265/\",\"timeToSync\":110,\"timeToReceiveMessage\":4042}",
  "{\"datetime\":\"Sat Mar 19 2022 12:23:07 GMT-0700 (Pacific Daylight Time)\",\"node\":\"http://54.177.214.21:14265/\",\"timeToSync\":111,\"timeToReceiveMessage\":1669}",
  "{\"datetime\":\"Sat Mar 19 2022 12:23:10 GMT-0700 (Pacific Daylight Time)\",\"node\":\"http://54.177.214.21:14265/\",\"timeToSync\":109,\"timeToReceiveMessage\":2402}",
  "{\"datetime\":\"Sat Mar 19 2022 12:23:13 GMT-0700 (Pacific Daylight Time)\",\"node\":\"http://54.177.214.21:14265/\",\"timeToSync\":111,\"timeToReceiveMessage\":2570}",
  "{\"datetime\":\"Sat Mar 19 2022 12:23:20 GMT-0700 (Pacific Daylight Time)\",\"node\":\"http://54.177.214.21:14265/\",\"timeToSync\":105,\"timeToReceiveMessage\":6891}",
  "{\"datetime\":\"Sat Mar 19 2022 12:23:23 GMT-0700 (Pacific Daylight Time)\",\"node\":\"http://54.177.214.21:14265/\",\"timeToSync\":110,\"timeToReceiveMessage\":2960}",
  "{\"datetime\":\"Sat Mar 19 2022 12:26:23 GMT-0700 (Pacific Daylight Time)\",\"node\":\"http://54.177.214.21:14265/\",\"timeToSync\":282,\"timeToReceiveMessage\":646}",
  "{\"datetime\":\"Sat Mar 19 2022 12:26:24 GMT-0700 (Pacific Daylight Time)\",\"node\":\"http://54.177.214.21:14265/\",\"timeToSync\":120,\"timeToReceiveMessage\":895}",
  "{\"datetime\":\"Sat Mar 19 2022 12:26:29 GMT-0700 (Pacific Daylight Time)\",\"node\":\"http://54.177.214.21:14265/\",\"timeToSync\":114,\"timeToReceiveMessage\":4283}",
  "{\"datetime\":\"Sat Mar 19 2022 12:26:32 GMT-0700 (Pacific Daylight Time)\",\"node\":\"http://54.177.214.21:14265/\",\"timeToSync\":122,\"timeToReceiveMessage\":3468}",
  "{\"datetime\":\"Sat Mar 19 2022 12:26:35 GMT-0700 (Pacific Daylight Time)\",\"node\":\"http://54.177.214.21:14265/\",\"timeToSync\":112,\"timeToReceiveMessage\":2255}",
  "{\"datetime\":\"Sat Mar 19 2022 12:26:38 GMT-0700 (Pacific Daylight Time)\",\"node\":\"http://54.177.214.21:14265/\",\"timeToSync\":114,\"timeToReceiveMessage\":3146}",
  "{\"datetime\":\"Sat Mar 19 2022 12:26:44 GMT-0700 (Pacific Daylight Time)\",\"node\":\"http://54.177.214.21:14265/\",\"timeToSync\":108,\"timeToReceiveMessage\":6039}",
  "{\"datetime\":\"Sat Mar 19 2022 12:26:47 GMT-0700 (Pacific Daylight Time)\",\"node\":\"http://54.177.214.21:14265/\",\"timeToSync\":110,\"timeToReceiveMessage\":2564}",
  "{\"datetime\":\"Sat Mar 19 2022 12:26:48 GMT-0700 (Pacific Daylight Time)\",\"node\":\"http://54.177.214.21:14265/\",\"timeToSync\":110,\"timeToReceiveMessage\":1279}",
  "{\"datetime\":\"Sat Mar 19 2022 12:26:49 GMT-0700 (Pacific Daylight Time)\",\"node\":\"http://54.177.214.21:14265/\",\"timeToSync\":121,\"timeToReceiveMessage\":792}",
  "{\"datetime\":\"Sat Mar 19 2022 12:28:56 GMT-0700 (Pacific Daylight Time)\",\"node\":\"http://54.177.214.21:14265/\",\"timeToSync\":273,\"timeToReceiveMessage\":2264}",
  "{\"datetime\":\"Sat Mar 19 2022 12:29:00 GMT-0700 (Pacific Daylight Time)\",\"node\":\"http://54.177.214.21:14265/\",\"timeToSync\":114,\"timeToReceiveMessage\":3909}",
  "{\"datetime\":\"Sat Mar 19 2022 12:29:03 GMT-0700 (Pacific Daylight Time)\",\"node\":\"http://54.177.214.21:14265/\",\"timeToSync\":115,\"timeToReceiveMessage\":2732}",
  "{\"datetime\":\"Sat Mar 19 2022 12:29:07 GMT-0700 (Pacific Daylight Time)\",\"node\":\"http://54.177.214.21:14265/\",\"timeToSync\":109,\"timeToReceiveMessage\":3738}",
  "{\"datetime\":\"Sat Mar 19 2022 12:29:07 GMT-0700 (Pacific Daylight Time)\",\"node\":\"http://54.177.214.21:14265/\",\"timeToSync\":111,\"timeToReceiveMessage\":526}",
  "{\"datetime\":\"Sat Mar 19 2022 12:29:08 GMT-0700 (Pacific Daylight Time)\",\"node\":\"http://54.177.214.21:14265/\",\"timeToSync\":113,\"timeToReceiveMessage\":655}",
  "{\"datetime\":\"Sat Mar 19 2022 12:29:09 GMT-0700 (Pacific Daylight Time)\",\"node\":\"http://54.177.214.21:14265/\",\"timeToSync\":109,\"timeToReceiveMessage\":539}",
  "{\"datetime\":\"Sat Mar 19 2022 12:29:10 GMT-0700 (Pacific Daylight Time)\",\"node\":\"http://54.177.214.21:14265/\",\"timeToSync\":112,\"timeToReceiveMessage\":1484}",
  "{\"datetime\":\"Sat Mar 19 2022 12:29:11 GMT-0700 (Pacific Daylight Time)\",\"node\":\"http://54.177.214.21:14265/\",\"timeToSync\":116,\"timeToReceiveMessage\":391}",
  "{\"datetime\":\"Sat Mar 19 2022 12:29:19 GMT-0700 (Pacific Daylight Time)\",\"node\":\"http://54.177.214.21:14265/\",\"timeToSync\":113,\"timeToReceiveMessage\":7746}",
  "{\"datetime\":\"Sun Mar 20 2022 21:43:05 GMT-0700 (Pacific Daylight Time)\",\"node\":\"http://54.177.214.21:14265/\",\"timeToSync\":277,\"timeToReceiveMessage\":1030}",
  "{\"datetime\":\"Sun Mar 20 2022 21:43:08 GMT-0700 (Pacific Daylight Time)\",\"node\":\"http://54.177.214.21:14265/\",\"timeToSync\":112,\"timeToReceiveMessage\":2249}",
  "{\"datetime\":\"Sun Mar 20 2022 21:43:09 GMT-0700 (Pacific Daylight Time)\",\"node\":\"http://54.177.214.21:14265/\",\"timeToSync\":115,\"timeToReceiveMessage\":835}",
  "{\"datetime\":\"Sun Mar 20 2022 21:43:11 GMT-0700 (Pacific Daylight Time)\",\"node\":\"http://54.177.214.21:14265/\",\"timeToSync\":112,\"timeToReceiveMessage\":1667}",
  "{\"datetime\":\"Sun Mar 20 2022 21:43:13 GMT-0700 (Pacific Daylight Time)\",\"node\":\"http://54.177.214.21:14265/\",\"timeToSync\":110,\"timeToReceiveMessage\":1986}",
  "{\"datetime\":\"Sun Mar 20 2022 21:43:14 GMT-0700 (Pacific Daylight Time)\",\"node\":\"http://54.177.214.21:14265/\",\"timeToSync\":113,\"timeToReceiveMessage\":1163}",
  "{\"datetime\":\"Sun Mar 20 2022 21:43:15 GMT-0700 (Pacific Daylight Time)\",\"node\":\"http://54.177.214.21:14265/\",\"timeToSync\":109,\"timeToReceiveMessage\":1029}",
  "{\"datetime\":\"Sun Mar 20 2022 21:43:17 GMT-0700 (Pacific Daylight Time)\",\"node\":\"http://54.177.214.21:14265/\",\"timeToSync\":103,\"timeToReceiveMessage\":1687}",
  "{\"datetime\":\"Sun Mar 20 2022 21:43:24 GMT-0700 (Pacific Daylight Time)\",\"node\":\"http://54.177.214.21:14265/\",\"timeToSync\":111,\"timeToReceiveMessage\":6512}",
  "{\"datetime\":\"Sun Mar 20 2022 21:43:25 GMT-0700 (Pacific Daylight Time)\",\"node\":\"http://54.177.214.21:14265/\",\"timeToSync\":109,\"timeToReceiveMessage\":968}",
  "{\"datetime\":\"Sun Mar 20 2022 21:44:36 GMT-0700 (Pacific Daylight Time)\",\"node\":\"http://54.177.214.21:14265/\",\"timeToSync\":288,\"timeToReceiveMessage\":18826}",
  "{\"datetime\":\"Sun Mar 20 2022 21:44:36 GMT-0700 (Pacific Daylight Time)\",\"node\":\"http://54.177.214.21:14265/\",\"timeToSync\":114,\"timeToReceiveMessage\":348}",
  "{\"datetime\":\"Sun Mar 20 2022 21:44:38 GMT-0700 (Pacific Daylight Time)\",\"node\":\"http://54.177.214.21:14265/\",\"timeToSync\":105,\"timeToReceiveMessage\":1312}",
  "{\"datetime\":\"Sun Mar 20 2022 21:44:42 GMT-0700 (Pacific Daylight Time)\",\"node\":\"http://54.177.214.21:14265/\",\"timeToSync\":110,\"timeToReceiveMessage\":4248}",
  "{\"datetime\":\"Sun Mar 20 2022 21:44:43 GMT-0700 (Pacific Daylight Time)\",\"node\":\"http://54.177.214.21:14265/\",\"timeToSync\":115,\"timeToReceiveMessage\":1048}",
  "{\"datetime\":\"Sun Mar 20 2022 21:44:47 GMT-0700 (Pacific Daylight Time)\",\"node\":\"http://54.177.214.21:14265/\",\"timeToSync\":110,\"timeToReceiveMessage\":3074}",
  "{\"datetime\":\"Sun Mar 20 2022 21:44:55 GMT-0700 (Pacific Daylight Time)\",\"node\":\"http://54.177.214.21:14265/\",\"timeToSync\":111,\"timeToReceiveMessage\":8236}",
  "{\"datetime\":\"Sun Mar 20 2022 21:45:09 GMT-0700 (Pacific Daylight Time)\",\"node\":\"http://54.177.214.21:14265/\",\"timeToSync\":115,\"timeToReceiveMessage\":13504}",
  "{\"datetime\":\"Sun Mar 20 2022 21:45:11 GMT-0700 (Pacific Daylight Time)\",\"node\":\"http://54.177.214.21:14265/\",\"timeToSync\":109,\"timeToReceiveMessage\":1670}",
  "{\"datetime\":\"Sun Mar 20 2022 21:45:12 GMT-0700 (Pacific Daylight Time)\",\"node\":\"http://54.177.214.21:14265/\",\"timeToSync\":118,\"timeToReceiveMessage\":1229}",
  "{\"datetime\":\"Sun Mar 20 2022 21:55:37 GMT-0700 (Pacific Daylight Time)\",\"auth_node\":\"http://54.177.214.21:14265/\",\"sub_node\":\"http://18.139.227.144:14265/\",\"timeToSync\":2955,\"timeToReceiveMessage\":3332,\"same_auth_sub\":false}",
  "{\"datetime\":\"Sun Mar 20 2022 21:55:42 GMT-0700 (Pacific Daylight Time)\",\"auth_node\":\"http://54.177.214.21:14265/\",\"sub_node\":\"http://18.139.227.144:14265/\",\"timeToSync\":1127,\"timeToReceiveMessage\":4105,\"same_auth_sub\":false}",
  "{\"datetime\":\"Sun Mar 20 2022 21:55:45 GMT-0700 (Pacific Daylight Time)\",\"auth_node\":\"http://54.177.214.21:14265/\",\"sub_node\":\"http://18.139.227.144:14265/\",\"timeToSync\":1065,\"timeToReceiveMessage\":2308,\"same_auth_sub\":false}",
  "{\"datetime\":\"Sun Mar 20 2022 21:55:56 GMT-0700 (Pacific Daylight Time)\",\"auth_node\":\"http://54.177.214.21:14265/\",\"sub_node\":\"http://18.139.227.144:14265/\",\"timeToSync\":1109,\"timeToReceiveMessage\":9309,\"same_auth_sub\":false}",
  "{\"datetime\":\"Sun Mar 20 2022 21:56:00 GMT-0700 (Pacific Daylight Time)\",\"auth_node\":\"http://54.177.214.21:14265/\",\"sub_node\":\"http://18.139.227.144:14265/\",\"timeToSync\":1117,\"timeToReceiveMessage\":3290,\"same_auth_sub\":false}",
  "{\"datetime\":\"Sun Mar 20 2022 21:56:05 GMT-0700 (Pacific Daylight Time)\",\"auth_node\":\"http://54.177.214.21:14265/\",\"sub_node\":\"http://18.139.227.144:14265/\",\"timeToSync\":1024,\"timeToReceiveMessage\":3628,\"same_auth_sub\":false}",
  "{\"datetime\":\"Sun Mar 20 2022 21:56:08 GMT-0700 (Pacific Daylight Time)\",\"auth_node\":\"http://54.177.214.21:14265/\",\"sub_node\":\"http://18.139.227.144:14265/\",\"timeToSync\":1131,\"timeToReceiveMessage\":2109,\"same_auth_sub\":false}",
  "{\"datetime\":\"Sun Mar 20 2022 21:56:17 GMT-0700 (Pacific Daylight Time)\",\"auth_node\":\"http://54.177.214.21:14265/\",\"sub_node\":\"http://18.139.227.144:14265/\",\"timeToSync\":1042,\"timeToReceiveMessage\":6988,\"same_auth_sub\":false}",
  "{\"datetime\":\"Sun Mar 20 2022 21:56:21 GMT-0700 (Pacific Daylight Time)\",\"auth_node\":\"http://54.177.214.21:14265/\",\"sub_node\":\"http://18.139.227.144:14265/\",\"timeToSync\":1215,\"timeToReceiveMessage\":3311,\"same_auth_sub\":false}",
  "{\"datetime\":\"Sun Mar 20 2022 21:56:24 GMT-0700 (Pacific Daylight Time)\",\"auth_node\":\"http://54.177.214.21:14265/\",\"sub_node\":\"http://18.139.227.144:14265/\",\"timeToSync\":1137,\"timeToReceiveMessage\":1953,\"same_auth_sub\":false}",
  "{\"datetime\":\"Mon Mar 21 2022 07:22:32 GMT-0700 (Pacific Daylight Time)\",\"auth_node\":\"http://54.177.214.21:14265/\",\"sub_node\":\"http://18.139.227.144:14265/\",\"timeToSync\":2745,\"timeToReceiveMessage\":2493,\"same_auth_sub\":false}",
  "{\"datetime\":\"Mon Mar 21 2022 07:22:37 GMT-0700 (Pacific Daylight Time)\",\"auth_node\":\"http://54.177.214.21:14265/\",\"sub_node\":\"http://18.139.227.144:14265/\",\"timeToSync\":1138,\"timeToReceiveMessage\":3840,\"same_auth_sub\":false}",
  "{\"datetime\":\"Mon Mar 21 2022 07:22:43 GMT-0700 (Pacific Daylight Time)\",\"auth_node\":\"http://54.177.214.21:14265/\",\"sub_node\":\"http://18.139.227.144:14265/\",\"timeToSync\":1119,\"timeToReceiveMessage\":4677,\"same_auth_sub\":false}",
  "{\"datetime\":\"Mon Mar 21 2022 07:22:46 GMT-0700 (Pacific Daylight Time)\",\"auth_node\":\"http://54.177.214.21:14265/\",\"sub_node\":\"http://18.139.227.144:14265/\",\"timeToSync\":1211,\"timeToReceiveMessage\":1844,\"same_auth_sub\":false}",
  "{\"datetime\":\"Mon Mar 21 2022 07:22:51 GMT-0700 (Pacific Daylight Time)\",\"auth_node\":\"http://54.177.214.21:14265/\",\"sub_node\":\"http://18.139.227.144:14265/\",\"timeToSync\":1046,\"timeToReceiveMessage\":3360,\"same_auth_sub\":false}",
  "{\"datetime\":\"Mon Mar 21 2022 07:22:54 GMT-0700 (Pacific Daylight Time)\",\"auth_node\":\"http://54.177.214.21:14265/\",\"sub_node\":\"http://18.139.227.144:14265/\",\"timeToSync\":1117,\"timeToReceiveMessage\":2253,\"same_auth_sub\":false}",
  "{\"datetime\":\"Mon Mar 21 2022 07:22:58 GMT-0700 (Pacific Daylight Time)\",\"auth_node\":\"http://54.177.214.21:14265/\",\"sub_node\":\"http://18.139.227.144:14265/\",\"timeToSync\":1276,\"timeToReceiveMessage\":2491,\"same_auth_sub\":false}",
  "{\"datetime\":\"Mon Mar 21 2022 07:23:02 GMT-0700 (Pacific Daylight Time)\",\"auth_node\":\"http://54.177.214.21:14265/\",\"sub_node\":\"http://18.139.227.144:14265/\",\"timeToSync\":1090,\"timeToReceiveMessage\":3017,\"same_auth_sub\":false}",
  "{\"datetime\":\"Mon Mar 21 2022 07:23:09 GMT-0700 (Pacific Daylight Time)\",\"auth_node\":\"http://54.177.214.21:14265/\",\"sub_node\":\"http://18.139.227.144:14265/\",\"timeToSync\":996,\"timeToReceiveMessage\":6206,\"same_auth_sub\":false}",
  "{\"datetime\":\"Mon Mar 21 2022 07:23:13 GMT-0700 (Pacific Daylight Time)\",\"auth_node\":\"http://54.177.214.21:14265/\",\"sub_node\":\"http://18.139.227.144:14265/\",\"timeToSync\":1092,\"timeToReceiveMessage\":2969,\"same_auth_sub\":false}",
  "{\"datetime\":\"Mon Mar 21 2022 10:45:21 GMT-0700 (Pacific Daylight Time)\",\"auth_node\":\"http://54.177.214.21:14265/\",\"sub_node\":\"http://54.177.214.21:14265/\",\"timeToSync\":290,\"timeToReceiveMessage\":3107,\"same_auth_sub\":true}",
  "{\"datetime\":\"Mon Mar 21 2022 10:45:22 GMT-0700 (Pacific Daylight Time)\",\"auth_node\":\"http://54.177.214.21:14265/\",\"sub_node\":\"http://54.177.214.21:14265/\",\"timeToSync\":108,\"timeToReceiveMessage\":702,\"same_auth_sub\":true}",
  "{\"datetime\":\"Mon Mar 21 2022 10:45:24 GMT-0700 (Pacific Daylight Time)\",\"auth_node\":\"http://54.177.214.21:14265/\",\"sub_node\":\"http://54.177.214.21:14265/\",\"timeToSync\":110,\"timeToReceiveMessage\":1380,\"same_auth_sub\":true}",
  "{\"datetime\":\"Mon Mar 21 2022 10:45:27 GMT-0700 (Pacific Daylight Time)\",\"auth_node\":\"http://54.177.214.21:14265/\",\"sub_node\":\"http://54.177.214.21:14265/\",\"timeToSync\":106,\"timeToReceiveMessage\":3060,\"same_auth_sub\":true}",
  "{\"datetime\":\"Mon Mar 21 2022 10:45:29 GMT-0700 (Pacific Daylight Time)\",\"auth_node\":\"http://54.177.214.21:14265/\",\"sub_node\":\"http://54.177.214.21:14265/\",\"timeToSync\":114,\"timeToReceiveMessage\":1444,\"same_auth_sub\":true}",
  "{\"datetime\":\"Mon Mar 21 2022 10:45:31 GMT-0700 (Pacific Daylight Time)\",\"auth_node\":\"http://54.177.214.21:14265/\",\"sub_node\":\"http://54.177.214.21:14265/\",\"timeToSync\":114,\"timeToReceiveMessage\":1889,\"same_auth_sub\":true}",
  "{\"datetime\":\"Mon Mar 21 2022 10:45:33 GMT-0700 (Pacific Daylight Time)\",\"auth_node\":\"http://54.177.214.21:14265/\",\"sub_node\":\"http://54.177.214.21:14265/\",\"timeToSync\":114,\"timeToReceiveMessage\":2559,\"same_auth_sub\":true}",
  "{\"datetime\":\"Mon Mar 21 2022 10:45:37 GMT-0700 (Pacific Daylight Time)\",\"auth_node\":\"http://54.177.214.21:14265/\",\"sub_node\":\"http://54.177.214.21:14265/\",\"timeToSync\":109,\"timeToReceiveMessage\":3180,\"same_auth_sub\":true}",
  "{\"datetime\":\"Mon Mar 21 2022 10:45:42 GMT-0700 (Pacific Daylight Time)\",\"auth_node\":\"http://54.177.214.21:14265/\",\"sub_node\":\"http://54.177.214.21:14265/\",\"timeToSync\":107,\"timeToReceiveMessage\":5402,\"same_auth_sub\":true}",
  "{\"datetime\":\"Mon Mar 21 2022 10:45:43 GMT-0700 (Pacific Daylight Time)\",\"auth_node\":\"http://54.177.214.21:14265/\",\"sub_node\":\"http://54.177.214.21:14265/\",\"timeToSync\":106,\"timeToReceiveMessage\":844,\"same_auth_sub\":true}",
  "{\"datetime\":\"Mon Mar 21 2022 11:10:09 GMT-0700 (Pacific Daylight Time)\",\"auth_node\":\"http://54.177.214.21:14265/\",\"sub_node\":\"http://54.177.214.21:14265/\",\"timeToSync\":288,\"timeToReceiveMessage\":5288,\"same_auth_sub\":true}",
  "{\"datetime\":\"Mon Mar 21 2022 11:20:52 GMT-0700 (Pacific Daylight Time)\",\"auth_node\":\"http://54.177.214.21:14265/\",\"sub_node\":\"http://54.177.214.21:14265/\",\"timeToSync\":298,\"timeToReceiveMessage\":4622,\"same_auth_sub\":true}",
  "{\"datetime\":\"Mon Mar 21 2022 11:21:01 GMT-0700 (Pacific Daylight Time)\",\"auth_node\":\"http://54.177.214.21:14265/\",\"sub_node\":\"http://54.177.214.21:14265/\",\"timeToSync\":114,\"timeToReceiveMessage\":8865,\"same_auth_sub\":true}",
  "{\"datetime\":\"Mon Mar 21 2022 11:21:03 GMT-0700 (Pacific Daylight Time)\",\"auth_node\":\"http://54.177.214.21:14265/\",\"sub_node\":\"http://54.177.214.21:14265/\",\"timeToSync\":111,\"timeToReceiveMessage\":1645,\"same_auth_sub\":true}",
  "{\"datetime\":\"Mon Mar 21 2022 11:21:04 GMT-0700 (Pacific Daylight Time)\",\"auth_node\":\"http://54.177.214.21:14265/\",\"sub_node\":\"http://54.177.214.21:14265/\",\"timeToSync\":108,\"timeToReceiveMessage\":480,\"same_auth_sub\":true}",
  "{\"datetime\":\"Mon Mar 21 2022 11:21:08 GMT-0700 (Pacific Daylight Time)\",\"auth_node\":\"http://54.177.214.21:14265/\",\"sub_node\":\"http://54.177.214.21:14265/\",\"timeToSync\":111,\"timeToReceiveMessage\":4154,\"same_auth_sub\":true}",
  "{\"datetime\":\"Mon Mar 21 2022 11:21:12 GMT-0700 (Pacific Daylight Time)\",\"auth_node\":\"http://54.177.214.21:14265/\",\"sub_node\":\"http://54.177.214.21:14265/\",\"timeToSync\":115,\"timeToReceiveMessage\":3482,\"same_auth_sub\":true}",
  "{\"datetime\":\"Mon Mar 21 2022 11:21:15 GMT-0700 (Pacific Daylight Time)\",\"auth_node\":\"http://54.177.214.21:14265/\",\"sub_node\":\"http://54.177.214.21:14265/\",\"timeToSync\":110,\"timeToReceiveMessage\":3075,\"same_auth_sub\":true}",
  "{\"datetime\":\"Mon Mar 21 2022 11:21:18 GMT-0700 (Pacific Daylight Time)\",\"auth_node\":\"http://54.177.214.21:14265/\",\"sub_node\":\"http://54.177.214.21:14265/\",\"timeToSync\":111,\"timeToReceiveMessage\":3055,\"same_auth_sub\":true}",
  "{\"datetime\":\"Mon Mar 21 2022 11:21:20 GMT-0700 (Pacific Daylight Time)\",\"auth_node\":\"http://54.177.214.21:14265/\",\"sub_node\":\"http://54.177.214.21:14265/\",\"timeToSync\":115,\"timeToReceiveMessage\":1796,\"same_auth_sub\":true}",
  "{\"datetime\":\"Mon Mar 21 2022 11:21:29 GMT-0700 (Pacific Daylight Time)\",\"auth_node\":\"http://54.177.214.21:14265/\",\"sub_node\":\"http://54.177.214.21:14265/\",\"timeToSync\":119,\"timeToReceiveMessage\":8773,\"same_auth_sub\":true}",
  "{\"datetime\":\"Mon Mar 21 2022 11:25:23 GMT-0700 (Pacific Daylight Time)\",\"auth_node\":\"http://54.177.214.21:14265/\",\"sub_node\":\"http://54.177.214.21:14265/\",\"timeToSync\":282,\"timeToReceiveMessage\":1134,\"same_auth_sub\":true,\"local_pow\":false}",
  "{\"datetime\":\"Mon Mar 21 2022 11:25:24 GMT-0700 (Pacific Daylight Time)\",\"auth_node\":\"http://54.177.214.21:14265/\",\"sub_node\":\"http://54.177.214.21:14265/\",\"timeToSync\":104,\"timeToReceiveMessage\":972,\"same_auth_sub\":true,\"local_pow\":false}",
  "{\"datetime\":\"Mon Mar 21 2022 11:25:24 GMT-0700 (Pacific Daylight Time)\",\"auth_node\":\"http://54.177.214.21:14265/\",\"sub_node\":\"http://54.177.214.21:14265/\",\"timeToSync\":114,\"timeToReceiveMessage\":496,\"same_auth_sub\":true,\"local_pow\":false}",
  "{\"datetime\":\"Mon Mar 21 2022 11:25:26 GMT-0700 (Pacific Daylight Time)\",\"auth_node\":\"http://54.177.214.21:14265/\",\"sub_node\":\"http://54.177.214.21:14265/\",\"timeToSync\":107,\"timeToReceiveMessage\":1433,\"same_auth_sub\":true,\"local_pow\":false}",
  "{\"datetime\":\"Mon Mar 21 2022 11:25:30 GMT-0700 (Pacific Daylight Time)\",\"auth_node\":\"http://54.177.214.21:14265/\",\"sub_node\":\"http://54.177.214.21:14265/\",\"timeToSync\":116,\"timeToReceiveMessage\":3335,\"same_auth_sub\":true,\"local_pow\":false}",
  "{\"datetime\":\"Mon Mar 21 2022 11:25:30 GMT-0700 (Pacific Daylight Time)\",\"auth_node\":\"http://54.177.214.21:14265/\",\"sub_node\":\"http://54.177.214.21:14265/\",\"timeToSync\":121,\"timeToReceiveMessage\":693,\"same_auth_sub\":true,\"local_pow\":false}",
  "{\"datetime\":\"Mon Mar 21 2022 11:25:32 GMT-0700 (Pacific Daylight Time)\",\"auth_node\":\"http://54.177.214.21:14265/\",\"sub_node\":\"http://54.177.214.21:14265/\",\"timeToSync\":116,\"timeToReceiveMessage\":1468,\"same_auth_sub\":true,\"local_pow\":false}",
  "{\"datetime\":\"Mon Mar 21 2022 11:25:33 GMT-0700 (Pacific Daylight Time)\",\"auth_node\":\"http://54.177.214.21:14265/\",\"sub_node\":\"http://54.177.214.21:14265/\",\"timeToSync\":111,\"timeToReceiveMessage\":659,\"same_auth_sub\":true,\"local_pow\":false}",
  "{\"datetime\":\"Mon Mar 21 2022 11:25:36 GMT-0700 (Pacific Daylight Time)\",\"auth_node\":\"http://54.177.214.21:14265/\",\"sub_node\":\"http://54.177.214.21:14265/\",\"timeToSync\":108,\"timeToReceiveMessage\":2631,\"same_auth_sub\":true,\"local_pow\":false}",
  "{\"datetime\":\"Mon Mar 21 2022 11:25:38 GMT-0700 (Pacific Daylight Time)\",\"auth_node\":\"http://54.177.214.21:14265/\",\"sub_node\":\"http://54.177.214.21:14265/\",\"timeToSync\":110,\"timeToReceiveMessage\":1653,\"same_auth_sub\":true,\"local_pow\":false}",
  "{\"datetime\":\"Mon Mar 21 2022 12:22:24 GMT-0700 (Pacific Daylight Time)\",\"auth_node\":\"http://54.177.214.21:14265/\",\"sub_node\":\"http://54.177.214.21:14265/\",\"timeToSync\":269,\"timeToReceiveMessage\":1490,\"same_auth_sub\":true,\"local_pow\":false,\"packet_size_kb\":0}",
  "{\"datetime\":\"Mon Mar 21 2022 12:22:33 GMT-0700 (Pacific Daylight Time)\",\"auth_node\":\"http://54.177.214.21:14265/\",\"sub_node\":\"http://54.177.214.21:14265/\",\"timeToSync\":114,\"timeToReceiveMessage\":8674,\"same_auth_sub\":true,\"local_pow\":false,\"packet_size_kb\":1}",
  "{\"datetime\":\"Mon Mar 21 2022 12:22:34 GMT-0700 (Pacific Daylight Time)\",\"auth_node\":\"http://54.177.214.21:14265/\",\"sub_node\":\"http://54.177.214.21:14265/\",\"timeToSync\":117,\"timeToReceiveMessage\":835,\"same_auth_sub\":true,\"local_pow\":false,\"packet_size_kb\":1}",
  "{\"datetime\":\"Mon Mar 21 2022 12:22:35 GMT-0700 (Pacific Daylight Time)\",\"auth_node\":\"http://54.177.214.21:14265/\",\"sub_node\":\"http://54.177.214.21:14265/\",\"timeToSync\":107,\"timeToReceiveMessage\":798,\"same_auth_sub\":true,\"local_pow\":false,\"packet_size_kb\":1}",
  "{\"datetime\":\"Mon Mar 21 2022 12:22:36 GMT-0700 (Pacific Daylight Time)\",\"auth_node\":\"http://54.177.214.21:14265/\",\"sub_node\":\"http://54.177.214.21:14265/\",\"timeToSync\":114,\"timeToReceiveMessage\":907,\"same_auth_sub\":true,\"local_pow\":false,\"packet_size_kb\":1}",
  "{\"datetime\":\"Mon Mar 21 2022 12:22:38 GMT-0700 (Pacific Daylight Time)\",\"auth_node\":\"http://54.177.214.21:14265/\",\"sub_node\":\"http://54.177.214.21:14265/\",\"timeToSync\":111,\"timeToReceiveMessage\":1626,\"same_auth_sub\":true,\"local_pow\":false,\"packet_size_kb\":1}",
  "{\"datetime\":\"Mon Mar 21 2022 12:22:39 GMT-0700 (Pacific Daylight Time)\",\"auth_node\":\"http://54.177.214.21:14265/\",\"sub_node\":\"http://54.177.214.21:14265/\",\"timeToSync\":107,\"timeToReceiveMessage\":413,\"same_auth_sub\":true,\"local_pow\":false,\"packet_size_kb\":1}",
  "{\"datetime\":\"Mon Mar 21 2022 12:22:40 GMT-0700 (Pacific Daylight Time)\",\"auth_node\":\"http://54.177.214.21:14265/\",\"sub_node\":\"http://54.177.214.21:14265/\",\"timeToSync\":114,\"timeToReceiveMessage\":1224,\"same_auth_sub\":true,\"local_pow\":false,\"packet_size_kb\":1}",
  "{\"datetime\":\"Mon Mar 21 2022 12:22:41 GMT-0700 (Pacific Daylight Time)\",\"auth_node\":\"http://54.177.214.21:14265/\",\"sub_node\":\"http://54.177.214.21:14265/\",\"timeToSync\":104,\"timeToReceiveMessage\":1036,\"same_auth_sub\":true,\"local_pow\":false,\"packet_size_kb\":1}",
  "{\"datetime\":\"Mon Mar 21 2022 12:22:48 GMT-0700 (Pacific Daylight Time)\",\"auth_node\":\"http://54.177.214.21:14265/\",\"sub_node\":\"http://54.177.214.21:14265/\",\"timeToSync\":117,\"timeToReceiveMessage\":6673,\"same_auth_sub\":true,\"local_pow\":false,\"packet_size_kb\":1}",
  "{\"datetime\":\"Mon Mar 21 2022 12:22:49 GMT-0700 (Pacific Daylight Time)\",\"auth_node\":\"http://54.177.214.21:14265/\",\"sub_node\":\"http://54.177.214.21:14265/\",\"timeToSync\":115,\"timeToReceiveMessage\":796,\"same_auth_sub\":true,\"local_pow\":false,\"packet_size_kb\":1}",
  "{\"datetime\":\"Mon Mar 21 2022 12:22:52 GMT-0700 (Pacific Daylight Time)\",\"auth_node\":\"http://54.177.214.21:14265/\",\"sub_node\":\"http://54.177.214.21:14265/\",\"timeToSync\":107,\"timeToReceiveMessage\":3206,\"same_auth_sub\":true,\"local_pow\":false,\"packet_size_kb\":3}",
  "{\"datetime\":\"Mon Mar 21 2022 12:22:53 GMT-0700 (Pacific Daylight Time)\",\"auth_node\":\"http://54.177.214.21:14265/\",\"sub_node\":\"http://54.177.214.21:14265/\",\"timeToSync\":114,\"timeToReceiveMessage\":978,\"same_auth_sub\":true,\"local_pow\":false,\"packet_size_kb\":3}",
  "{\"datetime\":\"Mon Mar 21 2022 12:22:54 GMT-0700 (Pacific Daylight Time)\",\"auth_node\":\"http://54.177.214.21:14265/\",\"sub_node\":\"http://54.177.214.21:14265/\",\"timeToSync\":113,\"timeToReceiveMessage\":573,\"same_auth_sub\":true,\"local_pow\":false,\"packet_size_kb\":3}",
  "{\"datetime\":\"Mon Mar 21 2022 12:23:00 GMT-0700 (Pacific Daylight Time)\",\"auth_node\":\"http://54.177.214.21:14265/\",\"sub_node\":\"http://54.177.214.21:14265/\",\"timeToSync\":111,\"timeToReceiveMessage\":5719,\"same_auth_sub\":true,\"local_pow\":false,\"packet_size_kb\":3}",
  "{\"datetime\":\"Mon Mar 21 2022 12:23:03 GMT-0700 (Pacific Daylight Time)\",\"auth_node\":\"http://54.177.214.21:14265/\",\"sub_node\":\"http://54.177.214.21:14265/\",\"timeToSync\":109,\"timeToReceiveMessage\":2698,\"same_auth_sub\":true,\"local_pow\":false,\"packet_size_kb\":3}",
  "{\"datetime\":\"Mon Mar 21 2022 12:23:05 GMT-0700 (Pacific Daylight Time)\",\"auth_node\":\"http://54.177.214.21:14265/\",\"sub_node\":\"http://54.177.214.21:14265/\",\"timeToSync\":115,\"timeToReceiveMessage\":2287,\"same_auth_sub\":true,\"local_pow\":false,\"packet_size_kb\":3}",
  "{\"datetime\":\"Mon Mar 21 2022 12:23:08 GMT-0700 (Pacific Daylight Time)\",\"auth_node\":\"http://54.177.214.21:14265/\",\"sub_node\":\"http://54.177.214.21:14265/\",\"timeToSync\":106,\"timeToReceiveMessage\":2306,\"same_auth_sub\":true,\"local_pow\":false,\"packet_size_kb\":3}",
  "{\"datetime\":\"Mon Mar 21 2022 12:23:11 GMT-0700 (Pacific Daylight Time)\",\"auth_node\":\"http://54.177.214.21:14265/\",\"sub_node\":\"http://54.177.214.21:14265/\",\"timeToSync\":120,\"timeToReceiveMessage\":2848,\"same_auth_sub\":true,\"local_pow\":false,\"packet_size_kb\":3}",
  "{\"datetime\":\"Mon Mar 21 2022 12:23:15 GMT-0700 (Pacific Daylight Time)\",\"auth_node\":\"http://54.177.214.21:14265/\",\"sub_node\":\"http://54.177.214.21:14265/\",\"timeToSync\":111,\"timeToReceiveMessage\":3663,\"same_auth_sub\":true,\"local_pow\":false,\"packet_size_kb\":3}",
  "{\"datetime\":\"Mon Mar 21 2022 12:23:17 GMT-0700 (Pacific Daylight Time)\",\"auth_node\":\"http://54.177.214.21:14265/\",\"sub_node\":\"http://54.177.214.21:14265/\",\"timeToSync\":127,\"timeToReceiveMessage\":1591,\"same_auth_sub\":true,\"local_pow\":false,\"packet_size_kb\":3}",
  "{\"datetime\":\"Mon Mar 21 2022 12:23:22 GMT-0700 (Pacific Daylight Time)\",\"auth_node\":\"http://54.177.214.21:14265/\",\"sub_node\":\"http://54.177.214.21:14265/\",\"timeToSync\":117,\"timeToReceiveMessage\":5717,\"same_auth_sub\":true,\"local_pow\":false,\"packet_size_kb\":7}",
  "{\"datetime\":\"Mon Mar 21 2022 12:23:24 GMT-0700 (Pacific Daylight Time)\",\"auth_node\":\"http://54.177.214.21:14265/\",\"sub_node\":\"http://54.177.214.21:14265/\",\"timeToSync\":109,\"timeToReceiveMessage\":1586,\"same_auth_sub\":true,\"local_pow\":false,\"packet_size_kb\":7}",
  "{\"datetime\":\"Mon Mar 21 2022 12:23:26 GMT-0700 (Pacific Daylight Time)\",\"auth_node\":\"http://54.177.214.21:14265/\",\"sub_node\":\"http://54.177.214.21:14265/\",\"timeToSync\":111,\"timeToReceiveMessage\":1648,\"same_auth_sub\":true,\"local_pow\":false,\"packet_size_kb\":7}",
  "{\"datetime\":\"Mon Mar 21 2022 12:23:28 GMT-0700 (Pacific Daylight Time)\",\"auth_node\":\"http://54.177.214.21:14265/\",\"sub_node\":\"http://54.177.214.21:14265/\",\"timeToSync\":114,\"timeToReceiveMessage\":1996,\"same_auth_sub\":true,\"local_pow\":false,\"packet_size_kb\":7}",
  "{\"datetime\":\"Mon Mar 21 2022 12:23:33 GMT-0700 (Pacific Daylight Time)\",\"auth_node\":\"http://54.177.214.21:14265/\",\"sub_node\":\"http://54.177.214.21:14265/\",\"timeToSync\":114,\"timeToReceiveMessage\":4455,\"same_auth_sub\":true,\"local_pow\":false,\"packet_size_kb\":7}",
  "{\"datetime\":\"Mon Mar 21 2022 12:23:34 GMT-0700 (Pacific Daylight Time)\",\"auth_node\":\"http://54.177.214.21:14265/\",\"sub_node\":\"http://54.177.214.21:14265/\",\"timeToSync\":111,\"timeToReceiveMessage\":1306,\"same_auth_sub\":true,\"local_pow\":false,\"packet_size_kb\":7}",
  "{\"datetime\":\"Mon Mar 21 2022 12:23:35 GMT-0700 (Pacific Daylight Time)\",\"auth_node\":\"http://54.177.214.21:14265/\",\"sub_node\":\"http://54.177.214.21:14265/\",\"timeToSync\":108,\"timeToReceiveMessage\":638,\"same_auth_sub\":true,\"local_pow\":false,\"packet_size_kb\":7}",
  "{\"datetime\":\"Mon Mar 21 2022 12:23:47 GMT-0700 (Pacific Daylight Time)\",\"auth_node\":\"http://54.177.214.21:14265/\",\"sub_node\":\"http://54.177.214.21:14265/\",\"timeToSync\":107,\"timeToReceiveMessage\":12213,\"same_auth_sub\":true,\"local_pow\":false,\"packet_size_kb\":7}",
  "{\"datetime\":\"Mon Mar 21 2022 12:23:50 GMT-0700 (Pacific Daylight Time)\",\"auth_node\":\"http://54.177.214.21:14265/\",\"sub_node\":\"http://54.177.214.21:14265/\",\"timeToSync\":109,\"timeToReceiveMessage\":1998,\"same_auth_sub\":true,\"local_pow\":false,\"packet_size_kb\":7}",
  "{\"datetime\":\"Mon Mar 21 2022 12:23:54 GMT-0700 (Pacific Daylight Time)\",\"auth_node\":\"http://54.177.214.21:14265/\",\"sub_node\":\"http://54.177.214.21:14265/\",\"timeToSync\":106,\"timeToReceiveMessage\":3851,\"same_auth_sub\":true,\"local_pow\":false,\"packet_size_kb\":7}",
  "{\"datetime\":\"Mon Mar 21 2022 12:23:55 GMT-0700 (Pacific Daylight Time)\",\"auth_node\":\"http://54.177.214.21:14265/\",\"sub_node\":\"http://54.177.214.21:14265/\",\"timeToSync\":107,\"timeToReceiveMessage\":1376,\"same_auth_sub\":true,\"local_pow\":false,\"packet_size_kb\":15}",
  "{\"datetime\":\"Mon Mar 21 2022 12:23:59 GMT-0700 (Pacific Daylight Time)\",\"auth_node\":\"http://54.177.214.21:14265/\",\"sub_node\":\"http://54.177.214.21:14265/\",\"timeToSync\":114,\"timeToReceiveMessage\":3597,\"same_auth_sub\":true,\"local_pow\":false,\"packet_size_kb\":15}",
  "{\"datetime\":\"Mon Mar 21 2022 12:24:02 GMT-0700 (Pacific Daylight Time)\",\"auth_node\":\"http://54.177.214.21:14265/\",\"sub_node\":\"http://54.177.214.21:14265/\",\"timeToSync\":115,\"timeToReceiveMessage\":3193,\"same_auth_sub\":true,\"local_pow\":false,\"packet_size_kb\":15}",
  "{\"datetime\":\"Mon Mar 21 2022 12:24:04 GMT-0700 (Pacific Daylight Time)\",\"auth_node\":\"http://54.177.214.21:14265/\",\"sub_node\":\"http://54.177.214.21:14265/\",\"timeToSync\":112,\"timeToReceiveMessage\":1481,\"same_auth_sub\":true,\"local_pow\":false,\"packet_size_kb\":15}",
  "{\"datetime\":\"Mon Mar 21 2022 12:24:07 GMT-0700 (Pacific Daylight Time)\",\"auth_node\":\"http://54.177.214.21:14265/\",\"sub_node\":\"http://54.177.214.21:14265/\",\"timeToSync\":117,\"timeToReceiveMessage\":3190,\"same_auth_sub\":true,\"local_pow\":false,\"packet_size_kb\":15}",
  "{\"datetime\":\"Mon Mar 21 2022 12:24:14 GMT-0700 (Pacific Daylight Time)\",\"auth_node\":\"http://54.177.214.21:14265/\",\"sub_node\":\"http://54.177.214.21:14265/\",\"timeToSync\":107,\"timeToReceiveMessage\":6201,\"same_auth_sub\":true,\"local_pow\":false,\"packet_size_kb\":15}",
  "{\"datetime\":\"Mon Mar 21 2022 12:24:17 GMT-0700 (Pacific Daylight Time)\",\"auth_node\":\"http://54.177.214.21:14265/\",\"sub_node\":\"http://54.177.214.21:14265/\",\"timeToSync\":107,\"timeToReceiveMessage\":3149,\"same_auth_sub\":true,\"local_pow\":false,\"packet_size_kb\":15}",
  "{\"datetime\":\"Mon Mar 21 2022 12:24:26 GMT-0700 (Pacific Daylight Time)\",\"auth_node\":\"http://54.177.214.21:14265/\",\"sub_node\":\"http://54.177.214.21:14265/\",\"timeToSync\":119,\"timeToReceiveMessage\":8912,\"same_auth_sub\":true,\"local_pow\":false,\"packet_size_kb\":15}",
  "{\"datetime\":\"Mon Mar 21 2022 12:24:27 GMT-0700 (Pacific Daylight Time)\",\"auth_node\":\"http://54.177.214.21:14265/\",\"sub_node\":\"http://54.177.214.21:14265/\",\"timeToSync\":116,\"timeToReceiveMessage\":677,\"same_auth_sub\":true,\"local_pow\":false,\"packet_size_kb\":15}",
  "{\"datetime\":\"Mon Mar 21 2022 12:24:28 GMT-0700 (Pacific Daylight Time)\",\"auth_node\":\"http://54.177.214.21:14265/\",\"sub_node\":\"http://54.177.214.21:14265/\",\"timeToSync\":112,\"timeToReceiveMessage\":1130,\"same_auth_sub\":true,\"local_pow\":false,\"packet_size_kb\":15}",
  "{\"datetime\":\"Mon Mar 21 2022 12:24:29 GMT-0700 (Pacific Daylight Time)\",\"auth_node\":\"http://54.177.214.21:14265/\",\"sub_node\":\"http://54.177.214.21:14265/\",\"timeToSync\":115,\"timeToReceiveMessage\":790,\"same_auth_sub\":true,\"local_pow\":false,\"packet_size_kb\":31}",
  "{\"datetime\":\"Mon Mar 21 2022 12:24:30 GMT-0700 (Pacific Daylight Time)\",\"auth_node\":\"http://54.177.214.21:14265/\",\"sub_node\":\"http://54.177.214.21:14265/\",\"timeToSync\":104,\"timeToReceiveMessage\":456,\"same_auth_sub\":true,\"local_pow\":false,\"packet_size_kb\":31}",
  "{\"datetime\":\"Mon Mar 21 2022 12:24:33 GMT-0700 (Pacific Daylight Time)\",\"auth_node\":\"http://54.177.214.21:14265/\",\"sub_node\":\"http://54.177.214.21:14265/\",\"timeToSync\":107,\"timeToReceiveMessage\":2856,\"same_auth_sub\":true,\"local_pow\":false,\"packet_size_kb\":31}",
  "{\"datetime\":\"Mon Mar 21 2022 12:24:34 GMT-0700 (Pacific Daylight Time)\",\"auth_node\":\"http://54.177.214.21:14265/\",\"sub_node\":\"http://54.177.214.21:14265/\",\"timeToSync\":113,\"timeToReceiveMessage\":1306,\"same_auth_sub\":true,\"local_pow\":false,\"packet_size_kb\":31}",
  "{\"datetime\":\"Mon Mar 21 2022 12:24:36 GMT-0700 (Pacific Daylight Time)\",\"auth_node\":\"http://54.177.214.21:14265/\",\"sub_node\":\"http://54.177.214.21:14265/\",\"timeToSync\":107,\"timeToReceiveMessage\":1295,\"same_auth_sub\":true,\"local_pow\":false,\"packet_size_kb\":31}",
  "{\"datetime\":\"Mon Mar 21 2022 12:24:43 GMT-0700 (Pacific Daylight Time)\",\"auth_node\":\"http://54.177.214.21:14265/\",\"sub_node\":\"http://54.177.214.21:14265/\",\"timeToSync\":118,\"timeToReceiveMessage\":7087,\"same_auth_sub\":true,\"local_pow\":false,\"packet_size_kb\":31}",
  "{\"datetime\":\"Mon Mar 21 2022 12:24:46 GMT-0700 (Pacific Daylight Time)\",\"auth_node\":\"http://54.177.214.21:14265/\",\"sub_node\":\"http://54.177.214.21:14265/\",\"timeToSync\":120,\"timeToReceiveMessage\":3045,\"same_auth_sub\":true,\"local_pow\":false,\"packet_size_kb\":31}",
  "{\"datetime\":\"Mon Mar 21 2022 12:24:51 GMT-0700 (Pacific Daylight Time)\",\"auth_node\":\"http://54.177.214.21:14265/\",\"sub_node\":\"http://54.177.214.21:14265/\",\"timeToSync\":114,\"timeToReceiveMessage\":4494,\"same_auth_sub\":true,\"local_pow\":false,\"packet_size_kb\":31}",
  "{\"datetime\":\"Mon Mar 21 2022 12:25:03 GMT-0700 (Pacific Daylight Time)\",\"auth_node\":\"http://54.177.214.21:14265/\",\"sub_node\":\"http://54.177.214.21:14265/\",\"timeToSync\":104,\"timeToReceiveMessage\":11564,\"same_auth_sub\":true,\"local_pow\":false,\"packet_size_kb\":31}",
  "{\"datetime\":\"Mon Mar 21 2022 12:25:47 GMT-0700 (Pacific Daylight Time)\",\"auth_node\":\"http://54.177.214.21:14265/\",\"sub_node\":\"http://54.177.214.21:14265/\",\"timeToSync\":277,\"timeToReceiveMessage\":9740,\"same_auth_sub\":true,\"local_pow\":false,\"packet_size_kb\":2000}",
  "{\"datetime\":\"Mon Mar 21 2022 12:26:05 GMT-0700 (Pacific Daylight Time)\",\"auth_node\":\"http://54.177.214.21:14265/\",\"sub_node\":\"http://54.177.214.21:14265/\",\"timeToSync\":111,\"timeToReceiveMessage\":18188,\"same_auth_sub\":true,\"local_pow\":false,\"packet_size_kb\":2000}",
  "{\"datetime\":\"Mon Mar 21 2022 12:27:06 GMT-0700 (Pacific Daylight Time)\",\"auth_node\":\"http://54.177.214.21:14265/\",\"sub_node\":\"http://54.177.214.21:14265/\",\"timeToSync\":108,\"timeToReceiveMessage\":60107,\"same_auth_sub\":true,\"local_pow\":false,\"packet_size_kb\":2000}",
  "{\"datetime\":\"Mon Mar 21 2022 12:27:39 GMT-0700 (Pacific Daylight Time)\",\"auth_node\":\"http://54.177.214.21:14265/\",\"sub_node\":\"http://54.177.214.21:14265/\",\"timeToSync\":109,\"timeToReceiveMessage\":33015,\"same_auth_sub\":true,\"local_pow\":false,\"packet_size_kb\":2000}",
  "{\"datetime\":\"Mon Mar 21 2022 12:27:55 GMT-0700 (Pacific Daylight Time)\",\"auth_node\":\"http://54.177.214.21:14265/\",\"sub_node\":\"http://54.177.214.21:14265/\",\"timeToSync\":111,\"timeToReceiveMessage\":16043,\"same_auth_sub\":true,\"local_pow\":false,\"packet_size_kb\":2000}",
  "{\"datetime\":\"Mon Mar 21 2022 12:29:06 GMT-0700 (Pacific Daylight Time)\",\"auth_node\":\"http://54.177.214.21:14265/\",\"sub_node\":\"http://54.177.214.21:14265/\",\"timeToSync\":116,\"timeToReceiveMessage\":70855,\"same_auth_sub\":true,\"local_pow\":false,\"packet_size_kb\":2000}",
  "{\"datetime\":\"Mon Mar 21 2022 12:30:03 GMT-0700 (Pacific Daylight Time)\",\"auth_node\":\"http://54.177.214.21:14265/\",\"sub_node\":\"http://54.177.214.21:14265/\",\"timeToSync\":108,\"timeToReceiveMessage\":56903,\"same_auth_sub\":true,\"local_pow\":false,\"packet_size_kb\":2000}",
  "{\"datetime\":\"Mon Mar 21 2022 12:30:30 GMT-0700 (Pacific Daylight Time)\",\"auth_node\":\"http://54.177.214.21:14265/\",\"sub_node\":\"http://54.177.214.21:14265/\",\"timeToSync\":116,\"timeToReceiveMessage\":27205,\"same_auth_sub\":true,\"local_pow\":false,\"packet_size_kb\":2000}",
  "{\"datetime\":\"Mon Mar 21 2022 12:30:37 GMT-0700 (Pacific Daylight Time)\",\"auth_node\":\"http://54.177.214.21:14265/\",\"sub_node\":\"http://54.177.214.21:14265/\",\"timeToSync\":116,\"timeToReceiveMessage\":5929,\"same_auth_sub\":true,\"local_pow\":false,\"packet_size_kb\":2000}",
  "{\"datetime\":\"Mon Mar 21 2022 12:30:58 GMT-0700 (Pacific Daylight Time)\",\"auth_node\":\"http://54.177.214.21:14265/\",\"sub_node\":\"http://54.177.214.21:14265/\",\"timeToSync\":115,\"timeToReceiveMessage\":21491,\"same_auth_sub\":true,\"local_pow\":false,\"packet_size_kb\":2000}",
  "{\"datetime\":\"Mon Mar 21 2022 12:31:55 GMT-0700 (Pacific Daylight Time)\",\"auth_node\":\"http://54.177.214.21:14265/\",\"sub_node\":\"http://54.177.214.21:14265/\",\"timeToSync\":103,\"timeToReceiveMessage\":56757,\"same_auth_sub\":true,\"local_pow\":false,\"packet_size_kb\":4000}",
  "{\"datetime\":\"Mon Mar 21 2022 12:31:57 GMT-0700 (Pacific Daylight Time)\",\"auth_node\":\"http://54.177.214.21:14265/\",\"sub_node\":\"http://54.177.214.21:14265/\",\"timeToSync\":106,\"timeToReceiveMessage\":1860,\"same_auth_sub\":true,\"local_pow\":false,\"packet_size_kb\":4000}",
  "{\"datetime\":\"Mon Mar 21 2022 12:33:00 GMT-0700 (Pacific Daylight Time)\",\"auth_node\":\"http://54.177.214.21:14265/\",\"sub_node\":\"http://54.177.214.21:14265/\",\"timeToSync\":115,\"timeToReceiveMessage\":62509,\"same_auth_sub\":true,\"local_pow\":false,\"packet_size_kb\":4000}",
  "{\"datetime\":\"Mon Mar 21 2022 12:35:02 GMT-0700 (Pacific Daylight Time)\",\"auth_node\":\"http://54.177.214.21:14265/\",\"sub_node\":\"http://54.177.214.21:14265/\",\"timeToSync\":110,\"timeToReceiveMessage\":121994,\"same_auth_sub\":true,\"local_pow\":false,\"packet_size_kb\":4000}",
  "{\"datetime\":\"Mon Mar 21 2022 12:36:14 GMT-0700 (Pacific Daylight Time)\",\"auth_node\":\"http://54.177.214.21:14265/\",\"sub_node\":\"http://54.177.214.21:14265/\",\"timeToSync\":109,\"timeToReceiveMessage\":72037,\"same_auth_sub\":true,\"local_pow\":false,\"packet_size_kb\":4000}",
  "{\"datetime\":\"Mon Mar 21 2022 12:37:15 GMT-0700 (Pacific Daylight Time)\",\"auth_node\":\"http://54.177.214.21:14265/\",\"sub_node\":\"http://54.177.214.21:14265/\",\"timeToSync\":115,\"timeToReceiveMessage\":60866,\"same_auth_sub\":true,\"local_pow\":false,\"packet_size_kb\":4000}",
  "{\"datetime\":\"Mon Mar 21 2022 12:39:33 GMT-0700 (Pacific Daylight Time)\",\"auth_node\":\"http://54.177.214.21:14265/\",\"sub_node\":\"http://54.177.214.21:14265/\",\"timeToSync\":108,\"timeToReceiveMessage\":137665,\"same_auth_sub\":true,\"local_pow\":false,\"packet_size_kb\":4000}",
  "{\"datetime\":\"Mon Mar 21 2022 12:39:47 GMT-0700 (Pacific Daylight Time)\",\"auth_node\":\"http://54.177.214.21:14265/\",\"sub_node\":\"http://54.177.214.21:14265/\",\"timeToSync\":113,\"timeToReceiveMessage\":13642,\"same_auth_sub\":true,\"local_pow\":false,\"packet_size_kb\":4000}",
  "{\"datetime\":\"Mon Mar 21 2022 12:40:00 GMT-0700 (Pacific Daylight Time)\",\"auth_node\":\"http://54.177.214.21:14265/\",\"sub_node\":\"http://54.177.214.21:14265/\",\"timeToSync\":114,\"timeToReceiveMessage\":13217,\"same_auth_sub\":true,\"local_pow\":false,\"packet_size_kb\":4000}",
  "{\"datetime\":\"Mon Mar 21 2022 12:40:45 GMT-0700 (Pacific Daylight Time)\",\"auth_node\":\"http://54.177.214.21:14265/\",\"sub_node\":\"http://54.177.214.21:14265/\",\"timeToSync\":115,\"timeToReceiveMessage\":44728,\"same_auth_sub\":true,\"local_pow\":false,\"packet_size_kb\":4000}",
  "{\"datetime\":\"Mon Mar 21 2022 12:41:04 GMT-0700 (Pacific Daylight Time)\",\"auth_node\":\"http://54.177.214.21:14265/\",\"sub_node\":\"http://54.177.214.21:14265/\",\"timeToSync\":114,\"timeToReceiveMessage\":18226,\"same_auth_sub\":true,\"local_pow\":false,\"packet_size_kb\":8000}",
  "{\"datetime\":\"Mon Mar 21 2022 12:41:21 GMT-0700 (Pacific Daylight Time)\",\"auth_node\":\"http://54.177.214.21:14265/\",\"sub_node\":\"http://54.177.214.21:14265/\",\"timeToSync\":111,\"timeToReceiveMessage\":17366,\"same_auth_sub\":true,\"local_pow\":false,\"packet_size_kb\":8000}",
  "{\"datetime\":\"Mon Mar 21 2022 12:42:12 GMT-0700 (Pacific Daylight Time)\",\"auth_node\":\"http://54.177.214.21:14265/\",\"sub_node\":\"http://54.177.214.21:14265/\",\"timeToSync\":114,\"timeToReceiveMessage\":50900,\"same_auth_sub\":true,\"local_pow\":false,\"packet_size_kb\":8000}",
  "{\"datetime\":\"Mon Mar 21 2022 14:51:22 GMT-0700 (Pacific Daylight Time)\",\"auth_node\":\"http://54.177.214.21:14265/\",\"sub_node\":\"http://54.177.214.21:14265/\",\"timeToSync\":283,\"timeToReceiveMessage\":88890,\"same_auth_sub\":true,\"local_pow\":false,\"packet_size_kb\":8000}",
  "{\"datetime\":\"Mon Mar 21 2022 14:52:01 GMT-0700 (Pacific Daylight Time)\",\"auth_node\":\"http://54.177.214.21:14265/\",\"sub_node\":\"http://54.177.214.21:14265/\",\"timeToSync\":111,\"timeToReceiveMessage\":38795,\"same_auth_sub\":true,\"local_pow\":false,\"packet_size_kb\":8000}",
  "{\"datetime\":\"Mon Mar 21 2022 14:52:57 GMT-0700 (Pacific Daylight Time)\",\"auth_node\":\"http://54.177.214.21:14265/\",\"sub_node\":\"http://54.177.214.21:14265/\",\"timeToSync\":109,\"timeToReceiveMessage\":56044,\"same_auth_sub\":true,\"local_pow\":false,\"packet_size_kb\":8000}",
  "{\"datetime\":\"Mon Mar 21 2022 14:54:31 GMT-0700 (Pacific Daylight Time)\",\"auth_node\":\"http://54.177.214.21:14265/\",\"sub_node\":\"http://54.177.214.21:14265/\",\"timeToSync\":107,\"timeToReceiveMessage\":93640,\"same_auth_sub\":true,\"local_pow\":false,\"packet_size_kb\":8000}",
  "{\"datetime\":\"Mon Mar 21 2022 14:54:51 GMT-0700 (Pacific Daylight Time)\",\"auth_node\":\"http://54.177.214.21:14265/\",\"sub_node\":\"http://54.177.214.21:14265/\",\"timeToSync\":115,\"timeToReceiveMessage\":19797,\"same_auth_sub\":true,\"local_pow\":false,\"packet_size_kb\":8000}",
  "{\"datetime\":\"Mon Mar 21 2022 14:55:38 GMT-0700 (Pacific Daylight Time)\",\"auth_node\":\"http://54.177.214.21:14265/\",\"sub_node\":\"http://54.177.214.21:14265/\",\"timeToSync\":104,\"timeToReceiveMessage\":46472,\"same_auth_sub\":true,\"local_pow\":false,\"packet_size_kb\":8000}",
  "{\"datetime\":\"Mon Mar 21 2022 15:08:47 GMT-0700 (Pacific Daylight Time)\",\"auth_node\":\"http://54.177.214.21:14265/\",\"sub_node\":\"http://54.177.214.21:14265/\",\"timeToSync\":280,\"timeToReceiveMessage\":14376,\"same_auth_sub\":true,\"local_pow\":true,\"packet_size_kb\":4000}",
  "{\"datetime\":\"Mon Mar 21 2022 15:10:56 GMT-0700 (Pacific Daylight Time)\",\"auth_node\":\"http://54.177.214.21:14265/\",\"sub_node\":\"http://54.177.214.21:14265/\",\"timeToSync\":112,\"timeToReceiveMessage\":128466,\"same_auth_sub\":true,\"local_pow\":true,\"packet_size_kb\":8000}",
  "{\"datetime\":\"Mon Mar 21 2022 15:11:45 GMT-0700 (Pacific Daylight Time)\",\"auth_node\":\"http://54.177.214.21:14265/\",\"sub_node\":\"http://54.177.214.21:14265/\",\"timeToSync\":117,\"timeToReceiveMessage\":48971,\"same_auth_sub\":true,\"local_pow\":true,\"packet_size_kb\":8000}",
  "{\"datetime\":\"Mon Mar 21 2022 15:13:45 GMT-0700 (Pacific Daylight Time)\",\"auth_node\":\"http://54.177.214.21:14265/\",\"sub_node\":\"http://54.177.214.21:14265/\",\"timeToSync\":123,\"timeToReceiveMessage\":120313,\"same_auth_sub\":true,\"local_pow\":true,\"packet_size_kb\":8000}",
  "{\"datetime\":\"Mon Mar 21 2022 15:14:46 GMT-0700 (Pacific Daylight Time)\",\"auth_node\":\"http://54.177.214.21:14265/\",\"sub_node\":\"http://54.177.214.21:14265/\",\"timeToSync\":117,\"timeToReceiveMessage\":60279,\"same_auth_sub\":true,\"local_pow\":true,\"packet_size_kb\":8000}",
  "{\"datetime\":\"Mon Mar 21 2022 15:14:57 GMT-0700 (Pacific Daylight Time)\",\"auth_node\":\"http://54.177.214.21:14265/\",\"sub_node\":\"http://54.177.214.21:14265/\",\"timeToSync\":109,\"timeToReceiveMessage\":11223,\"same_auth_sub\":true,\"local_pow\":true,\"packet_size_kb\":8000}"
]